CHANGES.txt
LICENSE.txt
README.txt
setup.py
src/collective/__init__.py
src/collective.folderposition.egg-info/PKG-INFO
src/collective.folderposition.egg-info/SOURCES.txt
src/collective.folderposition.egg-info/dependency_links.txt
src/collective.folderposition.egg-info/entry_points.txt
src/collective.folderposition.egg-info/namespace_packages.txt
src/collective.folderposition.egg-info/not-zip-safe
src/collective.folderposition.egg-info/requires.txt
src/collective.folderposition.egg-info/top_level.txt
src/collective/folderposition/__init__.py
src/collective/folderposition/configure.zcml
src/collective/folderposition/profiles/default/jsregistry.xml
src/collective/folderposition/profiles/default/skins.xml
src/collective/folderposition/skins/collective_folderposition/collective_folderposition.js
src/collective/folderposition/skins/collective_folderposition/collective_folderposition.py