Metadata-Version: 1.0
Name: collective.folderposition
Version: 1.0b4
Summary: Extended ordering controls for folder contents.
Home-page: http://pypi.python.org/pypi/collective.folderposition
Author: Laurence Rowe
Author-email: plone-developers@lists.sourceforge.net
License: GPL
Keywords: plone
Platform: UNKNOWN
Classifier: Framework :: Plone
Classifier: License :: OSI Approved :: GNU General Public License (GPL)
Classifier: Programming Language :: Python
